blehrm/UUIDS.py
blehrm/__init__.py
blehrm/interface.py
blehrm/registry.py
blehrm/clients/__init__.py
blehrm/clients/cl800.py
blehrm/clients/garmin_hrm_pro.py
blehrm/clients/mock_sensor.py
blehrm/clients/polar_h10.py
blehrm-0.1.4.dist-info/LICENSE
blehrm-0.1.4.dist-info/METADATA
blehrm-0.1.4.dist-info/WHEEL
blehrm-0.1.4.dist-info/top_level.txt
blehrm-0.1.4.dist-info/RECORD
