Metadata-Version: 2.1
Name: blehrm
Version: 0.1.4
Summary: Bluetooth Low Energy Heart Rate Monitoring
Author-email: Kieran Brennan <kbre93@gmail.com>
Project-URL: Homepage, https://github.com/kieranabrennan/blehrm
Project-URL: Bug Tracker, https://github.com/kieranabrennan/blehrm/issues
Classifier: Programming Language :: Python :: 3
Classifier: License :: OSI Approved :: MIT License
Classifier: Operating System :: OS Independent
Requires-Python: >=3.7
License-File: LICENSE
Requires-Dist: tabulate
Requires-Dist: bleak
Requires-Dist: numpy
Requires-Dist: asyncio
